ptr/__init__.py
ptr/agm/__init__.py
ptr/agm/api.py
ptr/agm/cache.py
ptr/agm/hash.py
ptr/agm/results.py
ptr/agm/simulation.py
ptr/axis.py
ptr/block/__init__.py
ptr/block/block.py
ptr/block/obs.py
ptr/block/slew.py
ptr/block/utils.py
ptr/cli.py
ptr/datetime/__init__.py
ptr/datetime/parser.py
ptr/datetime/time.py
ptr/datetime/window.py
ptr/element.py
ptr/esa/__init__.py
ptr/esa/export.py
ptr/esa/pointing_tool.py
ptr/html.py
ptr/metadata.py
ptr/prm.py
ptr/ptx.py
ptr/snippets.py
ptr/timeline.py
esa_ptr-1.4.dist-info/LICENSE.md
esa_ptr-1.4.dist-info/METADATA
esa_ptr-1.4.dist-info/WHEEL
esa_ptr-1.4.dist-info/entry_points.txt
esa_ptr-1.4.dist-info/RECORD
