Metadata-Version: 2.1
Name: esa-ptr
Version: 1.4
Summary: ESA Planning Timeline Request package
Home-page: https://juigitlab.esac.esa.int/python/ptr
License: BSD 3-Clause License
Keywords: esa,ptr,rosetta,juice
Author: Benoît Seignovert
Author-email: benoit.seignovert@univ-nantes.fr
Requires-Python: >=3.9,<4.0
Classifier: Development Status :: 4 - Beta
Classifier: Intended Audience :: Developers
Classifier: Intended Audience :: Science/Research
Classifier: License :: OSI Approved :: BSD License
Classifier: License :: Other/Proprietary License
Classifier: Natural Language :: English
Classifier: Programming Language :: Python
Classifier: Programming Language :: Python :: 3
Classifier: Programming Language :: Python :: 3.9
Classifier: Programming Language :: Python :: 3.10
Classifier: Programming Language :: Python :: 3.11
Classifier: Programming Language :: Python :: 3.12
Classifier: Topic :: Scientific/Engineering
Classifier: Topic :: Scientific/Engineering :: Astronomy
Project-URL: Bug Tracker, https://juigitlab.esac.esa.int/python/ptr/-/issues
Project-URL: Documentation, https://esa-ptr.readthedocs.io
Project-URL: Repository, https://juigitlab.esac.esa.int/python/ptr
